[
{"url": "https://en.wikipedia.org/wiki/%22Hello,_World!%22_program"},
{"url": "https://a3.animevost.org/tip/polnometrazhnyy-film/2479-hello-world.html"},
{"url": "https://www.programmingsimplified.com/c-hello-world-program"},
{"url": "https://www.youtube.com/watch?v=Yw6u6YkTgQ4"},
{"url": "https://www.programiz.com/c-programming/examples/print-sentence"},
{"url": "https://www.hello-world.com/"},
{"url": "https://hello-world-2019.fandom.com/wiki/Hello_World_(Film)"},
{"url": "https://www.quora.com/What-does-Hello-World-mean?share=1"},
{"url": "https://www.imdb.com/title/tt9418812/"},
{"url": "https://en.wikibooks.org/wiki/Computer_Programming/Hello_world"}
]